miniasync
