Metadata-Version: 1.2
Name: miniasync
Version: 0.1.2
Summary: miniasync is a small library build on top of asyncio to faciliate running small portions of asynchronous code in an otherwise synchronous application
Home-page: https://gitlab.com/alich75/miniasync
Author: Alice Heaton
Author-email: UNKNOWN
License: LGPLv3+
Keywords: asyncio
Platform: UNKNOWN
Classifier: Programming Language :: Python
Classifier: Programming Language :: Python :: 3.5
Classifier: License :: OSI Approved :: GNU Lesser General Public License v3 or later (LGPLv3+)
Requires-Python: >=3.5
